packpy/__init__.py
packpy/gui.py
packpy/main.py
pack_py_exe-0.2.0.dist-info/LICENSE
pack_py_exe-0.2.0.dist-info/METADATA
pack_py_exe-0.2.0.dist-info/WHEEL
pack_py_exe-0.2.0.dist-info/entry_points.txt
pack_py_exe-0.2.0.dist-info/top_level.txt
pack_py_exe-0.2.0.dist-info/RECORD
