Metadata-Version: 2.1
Name: pack-py-exe
Version: 0.2.0
Summary: One-click Python to EXE GUI tool (supports PyInstaller/Nuitka)
Home-page: https://github.com/JGZYES/pack-py
Author: JGZ_YES
Author-email: luoriguodu@qq.com
Classifier: Programming Language :: Python :: 3
Classifier: Programming Language :: Python :: 3.6
Classifier: Programming Language :: Python :: 3.7
Classifier: Programming Language :: Python :: 3.8
Classifier: Programming Language :: Python :: 3.9
Classifier: License :: OSI Approved :: MIT License
Classifier: Operating System :: Microsoft :: Windows
Requires-Python: >=3.6
License-File: LICENSE
Requires-Dist: PyQt5>=5.15.0
Requires-Dist: pyinstaller>=5.0
Requires-Dist: nuitka>=0.6.19
